dfindexeddb/__init__.py
dfindexeddb/errors.py
dfindexeddb/utils.py
dfindexeddb/version.py
dfindexeddb/indexeddb/__init__.py
dfindexeddb/indexeddb/cli.py
dfindexeddb/indexeddb/types.py
dfindexeddb/indexeddb/utils.py
dfindexeddb/indexeddb/chromium/__init__.py
dfindexeddb/indexeddb/chromium/blink.py
dfindexeddb/indexeddb/chromium/definitions.py
dfindexeddb/indexeddb/chromium/record.py
dfindexeddb/indexeddb/chromium/v8.py
dfindexeddb/indexeddb/firefox/__init__.py
dfindexeddb/indexeddb/firefox/definitions.py
dfindexeddb/indexeddb/firefox/gecko.py
dfindexeddb/indexeddb/firefox/record.py
dfindexeddb/indexeddb/safari/__init__.py
dfindexeddb/indexeddb/safari/definitions.py
dfindexeddb/indexeddb/safari/record.py
dfindexeddb/indexeddb/safari/webkit.py
dfindexeddb/leveldb/__init__.py
dfindexeddb/leveldb/cli.py
dfindexeddb/leveldb/definitions.py
dfindexeddb/leveldb/descriptor.py
dfindexeddb/leveldb/ldb.py
dfindexeddb/leveldb/log.py
dfindexeddb/leveldb/record.py
dfindexeddb/leveldb/utils.py
dfindexeddb/leveldb/plugins/__init__.py
dfindexeddb/leveldb/plugins/chrome_notifications.py
dfindexeddb/leveldb/plugins/interface.py
dfindexeddb/leveldb/plugins/manager.py
dfindexeddb/leveldb/plugins/notification_database_data_pb2.py
dfindexeddb-20251109.dist-info/licenses/LICENSE
dfindexeddb-20251109.dist-info/METADATA
dfindexeddb-20251109.dist-info/WHEEL
dfindexeddb-20251109.dist-info/entry_points.txt
dfindexeddb-20251109.dist-info/top_level.txt
dfindexeddb-20251109.dist-info/RECORD
