Metadata-Version: 2.4
Name: dfindexeddb
Version: 20251109
Summary: dfindexeddb is an experimental Python tool for performing digital forensic analysis of IndexedDB and leveldb files.
Author-email: Syd Pleno <sydp@google.com>
Maintainer-email: dfIndexeddb Developers <dfindexeddb-dev@googlegroups.com>
License-Expression: Apache-2.0
Project-URL: Homepage, https://github.com/google/dfindexeddb
Project-URL: Documentation, https://github.com/google/dfindexeddb/tree/main/docs
Project-URL: Repository, https://github.com/google/dfindexeddb
Project-URL: Bug Tracker, https://github.com/google/dfindexeddb/issues
Classifier: Development Status :: 3 - Alpha
Classifier: Programming Language :: Python
Requires-Python: >=3.9
License-File: LICENSE
Requires-Dist: python-snappy==0.6.1
Requires-Dist: zstd==1.5.5.1
Provides-Extra: plugins
Requires-Dist: protobuf; extra == "plugins"
Requires-Dist: dfdatetime; extra == "plugins"
Dynamic: license-file
